PHITS_tools/PHITS_tools.py
PHITS_tools/__init__.py
PHITS_tools/__main__.py
PHITS_tools/DCHAIN-Tools/dchain_tools.py
PHITS_tools/DCHAIN-Tools/readme.md
PHITS_tools/MC_materials/Compiled_MC_materials.json
PHITS_tools/MC_materials/PNNL_materials_compendium.json
PHITS_tools/MC_materials/README.md
PHITS_tools/MC_materials/manage_mc_materials.py
PHITS_tools/MC_materials/materials_compendium.csv
phits_tools-1.6.1.dist-info/METADATA
phits_tools-1.6.1.dist-info/WHEEL
phits_tools-1.6.1.dist-info/entry_points.txt
phits_tools-1.6.1.dist-info/licenses/LICENSE
phits_tools-1.6.1.dist-info/RECORD
