Metadata-Version: 2.4
Name: PHITS-Tools
Version: 1.6.1
Summary: Python module for parsing and post-processing output from the PHITS code
Project-URL: Documentation, https://github.com/Lindt8/PHITS-Tools#readme
Project-URL: Issues, https://github.com/Lindt8/PHITS-Tools/issues
Project-URL: Source, https://github.com/Lindt8/PHITS-Tools
Author-email: Hunter Ratliff <Lindt8@users.noreply.github.com>
License-Expression: MPL-2.0
License-File: LICENSE
Classifier: Operating System :: OS Independent
Classifier: Programming Language :: Python :: 3
Requires-Python: >=3.10
Requires-Dist: matplotlib>=3.10
Requires-Dist: numpy>=2.2
Requires-Dist: pandas>=2.2
Requires-Dist: scipy>=1.14
Requires-Dist: seaborn>=0.13
Provides-Extra: build
Requires-Dist: hatchling; extra == 'build'
Provides-Extra: develop
Requires-Dist: codecov-cli; extra == 'develop'
Requires-Dist: flake8; extra == 'develop'
Requires-Dist: pdoc3==0.10.0; extra == 'develop'
Requires-Dist: pytest-cov; extra == 'develop'
Requires-Dist: pytest>=6.0; extra == 'develop'
Provides-Extra: doc
Requires-Dist: pdoc3==0.10.0; extra == 'doc'
Provides-Extra: extras
Requires-Dist: munch>=2.5; extra == 'extras'
Requires-Dist: pyvista>=0.44; extra == 'extras'
Provides-Extra: test
Requires-Dist: flake8; extra == 'test'
Requires-Dist: pytest-cov; extra == 'test'
Requires-Dist: pytest>=6.0; extra == 'test'
